garminconnect/__init__.py
python_garminconnect_enhanced-0.0.2.dist-info/LICENSE
python_garminconnect_enhanced-0.0.2.dist-info/WHEEL
python_garminconnect_enhanced-0.0.2.dist-info/METADATA
python_garminconnect_enhanced-0.0.2.dist-info/RECORD
