Metadata-Version: 2.1
Name: python-garminconnect-enhanced
Version: 0.0.2
Summary: A fork of python-garminconnect with additional functionality to upload activities
License: MIT
Keywords: garmin connect,api,client,upload activity
Author: Marvin Straathof
Author-email: marvinstraathof@gmail.com
Requires-Python: >=3.9,<4.0
Classifier: License :: OSI Approved :: MIT License
Classifier: Operating System :: OS Independent
Classifier: Programming Language :: Python :: 3
Classifier: Programming Language :: Python :: 3.10
Classifier: Programming Language :: Python :: 3.9
Requires-Dist: cloudscraper (>=1.2.63,<2.0.0)
Requires-Dist: poetryup (>=0.10.0,<0.11.0)
Requires-Dist: requests (>=2.28.1,<3.0.0)
